{"isMarkdown":true,"isTranslated":false,"isActive":true,"flaws":{"bad_bcd_queries":[{"id":"bad_bcd_queries1","explanation":"No BCD data for query: api.RTCIceCandidatePairStats.remoteCandidateId","suggestion":null}]},"title":"RTCIceCandidatePairStats: remoteCandidateId property","mdn_url":"/en-US/docs/Web/API/RTCIceCandidatePairStats/remoteCandidateId","locale":"en-US","native":"English (US)","browserCompat":["api.RTCIceCandidatePairStats.remoteCandidateId"],"summary":"The RTCIceCandidatePairStats property\n  remoteCandidateId is a string that uniquely identifies\n  the remote ICE candidate which was analyzed to generate the\n  RTCIceCandidateStats used to compute the statistics for this pair of\n  candidates.","popularity":0,"modified":"2023-04-07T19:50:09.000Z","source":{"folder":"en-us/web/api/rtcicecandidatepairstats/remotecandidateid","github_url":"https://github.com/mdn/content/blob/main/files/en-us/web/api/rtcicecandidatepairstats/remotecandidateid/index.md","last_commit_url":"https://github.com/mdn/content/commit/954612667bafd71241a93e8554e8f11afc474ff3","filename":"index.md"},"short_title":"remoteCandidateId","parents":[{"uri":"/en-US/docs/Web","title":"References"},{"uri":"/en-US/docs/Web/API","title":"Web APIs"},{"uri":"/en-US/docs/Web/API/RTCIceCandidatePairStats","title":"RTCIceCandidatePairStats"},{"uri":"/en-US/docs/Web/API/RTCIceCandidatePairStats/remoteCandidateId","title":"remoteCandidateId"}],"pageTitle":"RTCIceCandidatePairStats: remoteCandidateId property - Web APIs | MDN","noIndexing":false,"hash":"7c670e6fcbfa5155020ab2c18b34dc7cb96ec196fed9a77dce2a384b2e3a2a45"}