{"isMarkdown":true,"isTranslated":false,"isActive":true,"flaws":{},"title":"Document: vlinkColor property","mdn_url":"/en-US/docs/Web/API/Document/vlinkColor","locale":"en-US","native":"English (US)","browserCompat":["api.Document.vlinkColor"],"summary":"The Document.vlinkColor property gets/sets the color of\n  links that the user has visited in the document.","popularity":0,"modified":"2023-04-07T05:52:28.000Z","source":{"folder":"en-us/web/api/document/vlinkcolor","github_url":"https://github.com/mdn/content/blob/main/files/en-us/web/api/document/vlinkcolor/index.md","last_commit_url":"https://github.com/mdn/content/commit/41a8b9c9832359d445d136b6d7a8a28737badc6b","filename":"index.md"},"short_title":"vlinkColor","parents":[{"uri":"/en-US/docs/Web","title":"References"},{"uri":"/en-US/docs/Web/API","title":"Web APIs"},{"uri":"/en-US/docs/Web/API/Document","title":"Document"},{"uri":"/en-US/docs/Web/API/Document/vlinkColor","title":"vlinkColor"}],"pageTitle":"Document: vlinkColor property - Web APIs | MDN","noIndexing":false,"hash":"09e4101c7d3b782a4a477fca06f3b81959aaf7f0481e317fc37f1f1fdb99ae25"}