{"isMarkdown":true,"isTranslated":false,"isActive":true,"flaws":{},"title":"XRReferenceSpace: reset event","mdn_url":"/en-US/docs/Web/API/XRReferenceSpace/reset_event","locale":"en-US","native":"English (US)","browserCompat":["api.XRReferenceSpace.reset_event"],"summary":"The reset event is sent to an XRReferenceSpace object when a discontinuity is detected in either the native origin or the effective origin, causing a jump in the position or orientation of objects oriented using the reference space. This is common when the user calibrates or recalibrates an XR device, or if the device automatically changes its origin after losing tracking of the user, then re-gaining it.","popularity":0,"modified":"2023-05-10T11:15:43.000Z","source":{"folder":"en-us/web/api/xrreferencespace/reset_event","github_url":"https://github.com/mdn/content/blob/main/files/en-us/web/api/xrreferencespace/reset_event/index.md","last_commit_url":"https://github.com/mdn/content/commit/76637f9517e4b0a57a3096a36f66b5e33a3f1051","filename":"index.md"},"short_title":"reset","parents":[{"uri":"/en-US/docs/Web","title":"References"},{"uri":"/en-US/docs/Web/API","title":"Web APIs"},{"uri":"/en-US/docs/Web/API/XRReferenceSpace","title":"XRReferenceSpace"},{"uri":"/en-US/docs/Web/API/XRReferenceSpace/reset_event","title":"reset"}],"pageTitle":"XRReferenceSpace: reset event - Web APIs | MDN","noIndexing":false,"hash":"35acee079be82f9601049ffe2ab3089e56304bce72f15c3ecea078449cc82626"}