{"isMarkdown":true,"isTranslated":false,"isActive":true,"flaws":{},"title":"AudioData: close() method","mdn_url":"/en-US/docs/Web/API/AudioData/close","locale":"en-US","native":"English (US)","browserCompat":["api.AudioData.close"],"summary":"The close() method of the AudioData interface clears all states and releases the reference to the media resource.","popularity":0,"modified":"2023-04-06T14:57:25.000Z","source":{"folder":"en-us/web/api/audiodata/close","github_url":"https://github.com/mdn/content/blob/main/files/en-us/web/api/audiodata/close/index.md","last_commit_url":"https://github.com/mdn/content/commit/135b8311a5e3d12789e8421845be3ce026ef72b8","filename":"index.md"},"short_title":"close()","parents":[{"uri":"/en-US/docs/Web","title":"References"},{"uri":"/en-US/docs/Web/API","title":"Web APIs"},{"uri":"/en-US/docs/Web/API/AudioData","title":"AudioData"},{"uri":"/en-US/docs/Web/API/AudioData/close","title":"close()"}],"pageTitle":"AudioData: close() method - Web APIs | MDN","noIndexing":false,"hash":"fd5bf0ee48779b2971c78e2d4a7637ead11384e7c32863cf9b9ef356d1c51928"}