{"isMarkdown":true,"isTranslated":false,"isActive":true,"flaws":{"bad_bcd_queries":[{"id":"bad_bcd_queries1","explanation":"No BCD data for query: http.headers.Sec-WebSocket-Accept","suggestion":null}]},"title":"Sec-WebSocket-Accept","mdn_url":"/en-US/docs/Web/HTTP/Headers/Sec-WebSocket-Accept","locale":"en-US","native":"English (US)","browserCompat":["http.headers.Sec-WebSocket-Accept"],"summary":"The Sec-WebSocket-Accept header is used in the websocket opening\n  handshake. It would appear in the response headers. That is, this is header is sent from\n  server to client to inform that server is willing to initiate a websocket connection.","popularity":0.0029,"modified":"2023-04-10T19:47:15.000Z","source":{"folder":"en-us/web/http/headers/sec-websocket-accept","github_url":"https://github.com/mdn/content/blob/main/files/en-us/web/http/headers/sec-websocket-accept/index.md","last_commit_url":"https://github.com/mdn/content/commit/0880a90f3811475d78bc4b2c344eb4146f25f66c","filename":"index.md"},"short_title":"Sec-WebSocket-Accept","parents":[{"uri":"/en-US/docs/Web","title":"References"},{"uri":"/en-US/docs/Web/HTTP","title":"HTTP"},{"uri":"/en-US/docs/Web/HTTP/Headers","title":"HTTP headers"},{"uri":"/en-US/docs/Web/HTTP/Headers/Sec-WebSocket-Accept","title":"Sec-WebSocket-Accept"}],"pageTitle":"Sec-WebSocket-Accept - HTTP | MDN","noIndexing":false,"hash":"d5fa03eb3878ae62fd08cf47f3118b24afca3f4ef1b5b2021b6fa80df699fcc3"}