{"isMarkdown":true,"isTranslated":false,"isActive":true,"flaws":{},"title":"Window: orientation property","mdn_url":"/en-US/docs/Web/API/Window/orientation","locale":"en-US","native":"English (US)","browserCompat":["api.Window.orientation"],"summary":"Returns the orientation in degrees (in 90-degree increments) of the viewport relative to the device's natural orientation.","popularity":0.004,"modified":"2023-04-08T06:57:07.000Z","source":{"folder":"en-us/web/api/window/orientation","github_url":"https://github.com/mdn/content/blob/main/files/en-us/web/api/window/orientation/index.md","last_commit_url":"https://github.com/mdn/content/commit/cc070123f72376faec06e36622c4fc723a75325f","filename":"index.md"},"short_title":"orientation","parents":[{"uri":"/en-US/docs/Web","title":"References"},{"uri":"/en-US/docs/Web/API","title":"Web APIs"},{"uri":"/en-US/docs/Web/API/Window","title":"Window"},{"uri":"/en-US/docs/Web/API/Window/orientation","title":"orientation"}],"pageTitle":"Window: orientation property - Web APIs | MDN","noIndexing":false,"hash":"9f2434370da7a115ef3acb64e33fbc893feca87b764dac77fe79cd8e9a887385"}