{"doc":{"isMarkdown":true,"isTranslated":false,"isActive":true,"flaws":{},"title":"RTCSessionDescription: toJSON() method","mdn_url":"/en-US/docs/Web/API/RTCSessionDescription/toJSON","locale":"en-US","native":"English (US)","browserCompat":["api.RTCSessionDescription.toJSON"],"sidebarHTML":"<ol><li><strong><a href=\"/en-US/docs/Web/API/WebRTC_API\">WebRTC API</a></strong></li><li><strong><a href=\"/en-US/docs/Web/API/RTCSessionDescription\"><code>RTCSessionDescription</code></a></strong></li><li class=\"toggle\"><details open=\"\"><summary>Constructor</summary><ol><li><a href=\"/en-US/docs/Web/API/RTCSessionDescription/RTCSessionDescription\"><code>RTCSessionDescription()</code></a><abbr class=\"icon icon-deprecated\" title=\"Deprecated. Not for use in new websites.\">\n  <span class=\"visually-hidden\">Deprecated</span>\n</abbr></li></ol></details></li><li class=\"toggle\"><details open=\"\"><summary>Instance properties</summary><ol><li><a href=\"/en-US/docs/Web/API/RTCSessionDescription/sdp\"><code>sdp</code></a></li><li><a href=\"/en-US/docs/Web/API/RTCSessionDescription/type\"><code>type</code></a></li></ol></details></li><li class=\"toggle\"><details open=\"\"><summary>Instance methods</summary><ol><li><em><code>toJSON()</code> </em></li></ol></details></li><li class=\"toggle\"><details open=\"\"><summary>Related pages for WebRTC</summary><ol><li><a href=\"/en-US/docs/Web/API/MediaDevices/getUserMedia\"><code>MediaDevices.getUserMedia()</code></a></li><li><a href=\"/en-US/docs/Web/API/Navigator/mediaDevices\"><code>Navigator.mediaDevices</code></a></li><li><a href=\"/en-US/docs/Web/API/RTCCertificate\"><code>RTCCertificate</code></a></li><li><a href=\"/en-US/docs/Web/API/RTCDTMFSender\"><code>RTCDTMFSender</code></a></li><li><a href=\"/en-US/docs/Web/API/RTCDTMFToneChangeEvent\"><code>RTCDTMFToneChangeEvent</code></a></li><li><a href=\"/en-US/docs/Web/API/RTCDataChannel\"><code>RTCDataChannel</code></a></li><li><a href=\"/en-US/docs/Web/API/RTCDataChannelEvent\"><code>RTCDataChannelEvent</code></a></li><li><a href=\"/en-US/docs/Web/API/RTCDtlsTransport\"><code>RTCDtlsTransport</code></a></li><li><a href=\"/en-US/docs/Web/API/RTCEncodedAudioFrame\"><code>RTCEncodedAudioFrame</code></a></li><li><a href=\"/en-US/docs/Web/API/RTCEncodedVideoFrame\"><code>RTCEncodedVideoFrame</code></a></li><li><a href=\"/en-US/docs/Web/API/RTCErrorEvent\"><code>RTCErrorEvent</code></a></li><li><a href=\"/en-US/docs/Web/API/RTCIceCandidate\"><code>RTCIceCandidate</code></a></li><li><a href=\"/en-US/docs/Web/API/RTCIceTransport\"><code>RTCIceTransport</code></a></li><li><a href=\"/en-US/docs/Web/API/RTCPeerConnection\"><code>RTCPeerConnection</code></a></li><li><a href=\"/en-US/docs/Web/API/RTCPeerConnectionIceErrorEvent\"><code>RTCPeerConnectionIceErrorEvent</code></a></li><li><a href=\"/en-US/docs/Web/API/RTCPeerConnectionIceEvent\"><code>RTCPeerConnectionIceEvent</code></a></li><li><a href=\"/en-US/docs/Web/API/RTCRtpReceiver\"><code>RTCRtpReceiver</code></a></li><li><a href=\"/en-US/docs/Web/API/RTCRtpReceiver/transform\"><code>RTCRtpReceiver.transform</code></a></li><li><a href=\"/en-US/docs/Web/API/RTCRtpScriptTransform\"><code>RTCRtpScriptTransform</code></a></li><li><a href=\"/en-US/docs/Web/API/RTCRtpScriptTransformer\"><code>RTCRtpScriptTransformer</code></a></li><li><a href=\"/en-US/docs/Web/API/RTCRtpSender\"><code>RTCRtpSender</code></a></li><li><a href=\"/en-US/docs/Web/API/RTCRtpSender/transform\"><code>RTCRtpSender.transform</code></a></li><li><a href=\"/en-US/docs/Web/API/RTCRtpTransceiver\"><code>RTCRtpTransceiver</code></a></li><li><a href=\"/en-US/docs/Web/API/RTCSctpTransport\"><code>RTCSctpTransport</code></a></li><li><a href=\"/en-US/docs/Web/API/RTCStatsReport\"><code>RTCStatsReport</code></a></li><li><a href=\"/en-US/docs/Web/API/RTCTrackEvent\"><code>RTCTrackEvent</code></a></li><li><a href=\"/en-US/docs/Web/API/RTCTransformEvent\"><code>RTCTransformEvent</code></a></li></ol></details></li></ol>","sidebarMacro":"APIRef","body":[{"type":"prose","value":{"id":null,"title":null,"isH3":false,"content":"<p>\n  The <strong><code>RTCSessionDescription.toJSON()</code></strong> method generates a\n  <a href=\"/en-US/docs/Glossary/JSON\">JSON</a> description of the object. Both properties,\n  <a href=\"/en-US/docs/Web/API/RTCSessionDescription/type\" title=\"type\"><code>type</code></a> and\n  <a href=\"/en-US/docs/Web/API/RTCSessionDescription/sdp\" title=\"sdp\"><code>sdp</code></a>, are contained in the generated JSON.\n</p>"}},{"type":"prose","value":{"id":"syntax","title":"Syntax","isH3":false,"content":"<div class=\"code-example\"><p class=\"example-header\"><span class=\"language-name\">js</span></p><pre class=\"brush: js notranslate\"><code><span class=\"token function\">toJSON</span><span class=\"token punctuation\">(</span><span class=\"token punctuation\">)</span>\n</code></pre></div>"}},{"type":"prose","value":{"id":"parameters","title":"Parameters","isH3":true,"content":"<p>None.</p>"}},{"type":"prose","value":{"id":"return_value","title":"Return value","isH3":true,"content":"<p>A <a href=\"/en-US/docs/Web/JavaScript/Reference/Global_Objects/JSON\"><code>JSON</code></a> object containing the following properties:</p>\n<dl>\n  <dt id=\"type\"><a href=\"#type\"><code>type</code></a></dt>\n  <dd>\n    <p>One of the following: <code>\"offer\"</code>, <code>\"answer\"</code>, <code>\"pranswer\"</code> or <code>null</code>.</p>\n  </dd>\n  <dt id=\"sdp\"><a href=\"#sdp\"><code>sdp</code></a></dt>\n  <dd>\n    <p>Either <code>null</code> or the <a href=\"/en-US/docs/Glossary/SDP\">SDP</a> message string corresponding to <a href=\"/en-US/docs/Web/API/RTCSessionDescription/sdp\"><code>RTCSessionDescription.sdp</code></a> property.</p>\n  </dd>\n</dl>"}},{"type":"prose","value":{"id":"example","title":"Example","isH3":false,"content":"<div class=\"code-example\"><p class=\"example-header\"><span class=\"language-name\">js</span></p><pre class=\"brush: js notranslate\"><code><span class=\"token comment\">// sd is a RTCSessionDescriptor</span>\n\n<span class=\"token function\">alert</span><span class=\"token punctuation\">(</span><span class=\"token constant\">JSON</span><span class=\"token punctuation\">.</span><span class=\"token function\">stringify</span><span class=\"token punctuation\">(</span>sd<span class=\"token punctuation\">)</span><span class=\"token punctuation\">)</span><span class=\"token punctuation\">;</span> <span class=\"token comment\">// This call the toJSON() method behind the scene.</span>\n</code></pre></div>"}},{"type":"specifications","value":{"title":"Specifications","id":"specifications","isH3":false,"specifications":[{"bcdSpecificationURL":"https://w3c.github.io/webrtc-pc/#dom-rtcsessiondescription-tojson","title":"WebRTC: Real-Time Communication in Browsers"}],"query":"api.RTCSessionDescription.toJSON"}},{"type":"browser_compatibility","value":{"title":"Browser compatibility","id":"browser_compatibility","isH3":false,"query":"api.RTCSessionDescription.toJSON"}},{"type":"prose","value":{"id":"see_also","title":"See also","isH3":false,"content":"<ul>\n  <li><a href=\"/en-US/docs/Web/API/WebRTC_API\">WebRTC</a></li>\n</ul>"}}],"toc":[{"text":"Syntax","id":"syntax"},{"text":"Example","id":"example"},{"text":"Specifications","id":"specifications"},{"text":"Browser compatibility","id":"browser_compatibility"},{"text":"See also","id":"see_also"}],"summary":"The RTCSessionDescription.toJSON() method generates a\n  JSON description of the object. Both properties,\n  type and\n  sdp, are contained in the generated JSON.","popularity":0,"modified":"2023-04-08T06:00:31.000Z","source":{"folder":"en-us/web/api/rtcsessiondescription/tojson","github_url":"https://github.com/mdn/content/blob/main/files/en-us/web/api/rtcsessiondescription/tojson/index.md","last_commit_url":"https://github.com/mdn/content/commit/f2f9346c0c0e9f6676f2df9f1850933e274401de","filename":"index.md"},"short_title":"toJSON()","parents":[{"uri":"/en-US/docs/Web","title":"References"},{"uri":"/en-US/docs/Web/API","title":"Web APIs"},{"uri":"/en-US/docs/Web/API/RTCSessionDescription","title":"RTCSessionDescription"},{"uri":"/en-US/docs/Web/API/RTCSessionDescription/toJSON","title":"toJSON()"}],"pageTitle":"RTCSessionDescription: toJSON() method - Web APIs | MDN","noIndexing":false}}