{"isMarkdown":true,"isTranslated":false,"isActive":true,"flaws":{},"title":"SVGAnimatedString","mdn_url":"/en-US/docs/Web/API/SVGAnimatedString","locale":"en-US","native":"English (US)","browserCompat":["api.SVGAnimatedString"],"summary":"The SVGAnimatedString interface represents string attributes which can be animated from each SVG declaration. You need to create SVG attribute before doing anything else, everything should be declared inside this.","popularity":0.0012,"modified":"2023-02-19T08:53:53.000Z","source":{"folder":"en-us/web/api/svganimatedstring","github_url":"https://github.com/mdn/content/blob/main/files/en-us/web/api/svganimatedstring/index.md","last_commit_url":"https://github.com/mdn/content/commit/226ac33eb70ed5411dd2d68bd602c80cafd780b6","filename":"index.md"},"short_title":"SVGAnimatedString","parents":[{"uri":"/en-US/docs/Web","title":"References"},{"uri":"/en-US/docs/Web/API","title":"Web APIs"},{"uri":"/en-US/docs/Web/API/SVGAnimatedString","title":"SVGAnimatedString"}],"pageTitle":"SVGAnimatedString - Web APIs | MDN","noIndexing":false,"hash":"ac2a0a06688482d6c3f6287b4b935243ea3d0dc20c34d8b452376f6c22d6686e"}