{"isMarkdown":true,"isTranslated":false,"isActive":true,"flaws":{},"title":"text-indent","mdn_url":"/en-US/docs/Web/CSS/text-indent","locale":"en-US","native":"English (US)","browserCompat":["css.properties.text-indent"],"summary":"The text-indent CSS property sets the length of empty space (indentation) that is put before lines of text in a block.","popularity":0.0259,"modified":"2023-10-02T11:11:40.000Z","source":{"folder":"en-us/web/css/text-indent","github_url":"https://github.com/mdn/content/blob/main/files/en-us/web/css/text-indent/index.md","last_commit_url":"https://github.com/mdn/content/commit/bb652aaf3e38f3c7fef970a62f813047dffac879","filename":"index.md"},"short_title":"text-indent","parents":[{"uri":"/en-US/docs/Web","title":"References"},{"uri":"/en-US/docs/Web/CSS","title":"CSS"},{"uri":"/en-US/docs/Web/CSS/text-indent","title":"text-indent"}],"pageTitle":"text-indent - CSS: Cascading Style Sheets | MDN","noIndexing":false,"hash":"4fbd99cf3f1105db13cd61dc7011b0b299260b5dada83e14ce41710b5b159647"}