{"isMarkdown":true,"isTranslated":false,"isActive":true,"flaws":{},"title":"rgb()","mdn_url":"/en-US/docs/Web/CSS/color_value/rgb","locale":"en-US","native":"English (US)","browserCompat":["css.types.color.rgb"],"summary":"The rgb() functional notation expresses a color according to its red, green, and blue components. An optional alpha component represents the color's transparency.","popularity":0.0189,"modified":"2023-09-16T02:17:45.000Z","source":{"folder":"en-us/web/css/color_value/rgb","github_url":"https://github.com/mdn/content/blob/main/files/en-us/web/css/color_value/rgb/index.md","last_commit_url":"https://github.com/mdn/content/commit/d71f07e831c84f37c25e920571471d2ea032b63c","filename":"index.md"},"short_title":"rgb()","parents":[{"uri":"/en-US/docs/Web","title":"References"},{"uri":"/en-US/docs/Web/CSS","title":"CSS"},{"uri":"/en-US/docs/Web/CSS/color_value","title":"<color>"},{"uri":"/en-US/docs/Web/CSS/color_value/rgb","title":"rgb()"}],"pageTitle":"rgb() - CSS: Cascading Style Sheets | MDN","noIndexing":false,"hash":"fb330f2529f14770746f973291aae8a0497a7e21cd0a0cd9ea383d460087364d"}