{"isMarkdown":true,"isTranslated":false,"isActive":true,"flaws":{},"title":"user-modify","mdn_url":"/en-US/docs/Web/CSS/user-modify","locale":"en-US","native":"English (US)","browserCompat":["css.properties.user-modify"],"summary":"The user-modify property has no effect in Firefox. It was originally planned to determine whether or not the content of an element can be edited by a user.","popularity":0.0059,"modified":"2023-07-20T07:38:29.000Z","source":{"folder":"en-us/web/css/user-modify","github_url":"https://github.com/mdn/content/blob/main/files/en-us/web/css/user-modify/index.md","last_commit_url":"https://github.com/mdn/content/commit/c77cfcd17e85db6c1b93160c70668f2ff6c2809c","filename":"index.md"},"short_title":"user-modify","parents":[{"uri":"/en-US/docs/Web","title":"References"},{"uri":"/en-US/docs/Web/CSS","title":"CSS"},{"uri":"/en-US/docs/Web/CSS/user-modify","title":"user-modify"}],"pageTitle":"user-modify - CSS: Cascading Style Sheets | MDN","noIndexing":false,"hash":"bba5e4f103baff895bf5c32d70943d2ea2d9e47b5d65e31790d4a9c265052eff"}