{"isMarkdown":true,"isTranslated":false,"isActive":true,"flaws":{},"title":"CookieStore: getAll() method","mdn_url":"/en-US/docs/Web/API/CookieStore/getAll","locale":"en-US","native":"English (US)","browserCompat":["api.CookieStore.getAll"],"summary":"The getAll() method of the CookieStore interface returns a list of cookies that match the name or options passed to it. Passing no parameters will return all cookies for the current context.","popularity":0.0009,"modified":"2023-04-07T05:46:57.000Z","source":{"folder":"en-us/web/api/cookiestore/getall","github_url":"https://github.com/mdn/content/blob/main/files/en-us/web/api/cookiestore/getall/index.md","last_commit_url":"https://github.com/mdn/content/commit/d76defab4ca13261e9de81ae1df125345f847b0a","filename":"index.md"},"short_title":"getAll()","parents":[{"uri":"/en-US/docs/Web","title":"References"},{"uri":"/en-US/docs/Web/API","title":"Web APIs"},{"uri":"/en-US/docs/Web/API/CookieStore","title":"CookieStore"},{"uri":"/en-US/docs/Web/API/CookieStore/getAll","title":"getAll()"}],"pageTitle":"CookieStore: getAll() method - Web APIs | MDN","noIndexing":false,"hash":"36ba67b5de483e14ed1fe900c76bb62273962d7d3730e1235886b56c6c647546"}