{"isMarkdown":true,"isTranslated":false,"isActive":true,"flaws":{},"title":"VideoPlaybackQuality: droppedVideoFrames property","mdn_url":"/en-US/docs/Web/API/VideoPlaybackQuality/droppedVideoFrames","locale":"en-US","native":"English (US)","browserCompat":["api.VideoPlaybackQuality.droppedVideoFrames"],"summary":"The read-only droppedVideoFrames\n  property of the VideoPlaybackQuality interface returns the number of\n  video frames which have been dropped rather than being displayed since the last time\n  the media was loaded into the HTMLVideoElement.","popularity":0,"modified":"2023-04-08T06:43:07.000Z","source":{"folder":"en-us/web/api/videoplaybackquality/droppedvideoframes","github_url":"https://github.com/mdn/content/blob/main/files/en-us/web/api/videoplaybackquality/droppedvideoframes/index.md","last_commit_url":"https://github.com/mdn/content/commit/532ecbca7b68e7defa4612bc7b00885a13163641","filename":"index.md"},"short_title":"droppedVideoFrames","parents":[{"uri":"/en-US/docs/Web","title":"References"},{"uri":"/en-US/docs/Web/API","title":"Web APIs"},{"uri":"/en-US/docs/Web/API/VideoPlaybackQuality","title":"VideoPlaybackQuality"},{"uri":"/en-US/docs/Web/API/VideoPlaybackQuality/droppedVideoFrames","title":"droppedVideoFrames"}],"pageTitle":"VideoPlaybackQuality: droppedVideoFrames property - Web APIs | MDN","noIndexing":false,"hash":"b42ff6c1f70e11392d42dd4a5656f97f8d2a877301ab3621dd7eba1fb2713840"}