{"isMarkdown":true,"isTranslated":false,"isActive":true,"flaws":{},"title":"Cache: matchAll() method","mdn_url":"/en-US/docs/Web/API/Cache/matchAll","locale":"en-US","native":"English (US)","browserCompat":["api.Cache.matchAll"],"summary":"The matchAll() method of the Cache\n  interface returns a Promise that resolves to an array of all matching\n  responses in the Cache object.","popularity":0.0009,"modified":"2023-05-31T09:59:11.000Z","source":{"folder":"en-us/web/api/cache/matchall","github_url":"https://github.com/mdn/content/blob/main/files/en-us/web/api/cache/matchall/index.md","last_commit_url":"https://github.com/mdn/content/commit/633a8bf8d2bb80d29f417e4ef6cd53fdeeda940d","filename":"index.md"},"short_title":"matchAll()","parents":[{"uri":"/en-US/docs/Web","title":"References"},{"uri":"/en-US/docs/Web/API","title":"Web APIs"},{"uri":"/en-US/docs/Web/API/Cache","title":"Cache"},{"uri":"/en-US/docs/Web/API/Cache/matchAll","title":"matchAll()"}],"pageTitle":"Cache: matchAll() method - Web APIs | MDN","noIndexing":false,"hash":"c8e397bb22022d56aa92c72235acc50f87c2850165884d9592e7554274200bfd"}