{"isMarkdown":true,"isTranslated":false,"isActive":true,"flaws":{},"title":"WebTransport: reliability property","mdn_url":"/en-US/docs/Web/API/WebTransport/reliability","locale":"en-US","native":"English (US)","browserCompat":["api.WebTransport.reliability"],"summary":"The reliability read-only property of the WebTransport interface indicates whether the connection supports reliable transports only, or whether it also supports unreliable transports (such as UDP).","popularity":0,"modified":"2023-05-19T13:07:38.000Z","source":{"folder":"en-us/web/api/webtransport/reliability","github_url":"https://github.com/mdn/content/blob/main/files/en-us/web/api/webtransport/reliability/index.md","last_commit_url":"https://github.com/mdn/content/commit/8315b27444fe66b1d7894af30db83be0ab9463d8","filename":"index.md"},"short_title":"reliability","parents":[{"uri":"/en-US/docs/Web","title":"References"},{"uri":"/en-US/docs/Web/API","title":"Web APIs"},{"uri":"/en-US/docs/Web/API/WebTransport","title":"WebTransport"},{"uri":"/en-US/docs/Web/API/WebTransport/reliability","title":"reliability"}],"pageTitle":"WebTransport: reliability property - Web APIs | MDN","noIndexing":false,"hash":"bff0522f912fbab5f0b0ab6e6dae6358013d0b63f76412689b4fcd103a7364b8"}