{"doc":{"isMarkdown":true,"isTranslated":false,"isActive":true,"flaws":{},"title":"mathsize","mdn_url":"/en-US/docs/Web/MathML/Global_attributes/mathsize","locale":"en-US","native":"English (US)","browserCompat":["mathml.global_attributes.mathsize"],"sidebarHTML":"\n <ol>\n  <li><a href=\"/en-US/docs/Web/MathML\"><strong>MathML</strong></a></li>\n  <li><strong>Guides</strong></li>\n  <li>\n    <ol>\n    <li><a href=\"/en-US/docs/Web/MathML/Authoring\">Authoring MathML</a></li>\n    <li><a href=\"/en-US/docs/Web/MathML/Fonts\">Fonts for MathML</a></li>\n    <li><a href=\"/en-US/docs/Web/MathML/Values\">MathML Attribute Values</a></li>\n    </ol>\n  </li>\n  <li><strong>Reference</strong></li>\n  <li class=\"toggle\">\n    <details>\n      <summary>Elements</summary>\n      <ol><li><a href=\"/en-US/docs/Web/MathML/Element/maction\"><code>&lt;maction&gt;</code></a><abbr class=\"icon icon-deprecated\" title=\"Deprecated. Not for use in new websites.\">\n  <span class=\"visually-hidden\">Deprecated</span>\n</abbr></li><li><a href=\"/en-US/docs/Web/MathML/Element/math\"><code>&lt;math&gt;</code></a></li><li><a href=\"/en-US/docs/Web/MathML/Element/menclose\"><code>&lt;menclose&gt;</code></a><abbr class=\"icon icon-nonstandard\" title=\"Non-standard. Check cross-browser support before using.\">\n    <span class=\"visually-hidden\">Non-standard</span>\n</abbr></li><li><a href=\"/en-US/docs/Web/MathML/Element/merror\"><code>&lt;merror&gt;</code></a></li><li><a href=\"/en-US/docs/Web/MathML/Element/mfenced\"><code>&lt;mfenced&gt;</code></a><abbr class=\"icon icon-nonstandard\" title=\"Non-standard. Check cross-browser support before using.\">\n    <span class=\"visually-hidden\">Non-standard</span>\n</abbr><abbr class=\"icon icon-deprecated\" title=\"Deprecated. Not for use in new websites.\">\n  <span class=\"visually-hidden\">Deprecated</span>\n</abbr></li><li><a href=\"/en-US/docs/Web/MathML/Element/mfrac\"><code>&lt;mfrac&gt;</code></a></li><li><a href=\"/en-US/docs/Web/MathML/Element/mi\"><code>&lt;mi&gt;</code></a></li><li><a href=\"/en-US/docs/Web/MathML/Element/mmultiscripts\"><code>&lt;mmultiscripts&gt;</code></a></li><li><a href=\"/en-US/docs/Web/MathML/Element/mn\"><code>&lt;mn&gt;</code></a></li><li><a href=\"/en-US/docs/Web/MathML/Element/mo\"><code>&lt;mo&gt;</code></a></li><li><a href=\"/en-US/docs/Web/MathML/Element/mover\"><code>&lt;mover&gt;</code></a></li><li><a href=\"/en-US/docs/Web/MathML/Element/mpadded\"><code>&lt;mpadded&gt;</code></a></li><li><a href=\"/en-US/docs/Web/MathML/Element/mphantom\"><code>&lt;mphantom&gt;</code></a></li><li><a href=\"/en-US/docs/Web/MathML/Element/mroot\"><code>&lt;mroot&gt;</code></a></li><li><a href=\"/en-US/docs/Web/MathML/Element/mrow\"><code>&lt;mrow&gt;</code></a></li><li><a href=\"/en-US/docs/Web/MathML/Element/ms\"><code>&lt;ms&gt;</code></a></li><li><a href=\"/en-US/docs/Web/MathML/Element/mspace\"><code>&lt;mspace&gt;</code></a></li><li><a href=\"/en-US/docs/Web/MathML/Element/msqrt\"><code>&lt;msqrt&gt;</code></a></li><li><a href=\"/en-US/docs/Web/MathML/Element/mstyle\"><code>&lt;mstyle&gt;</code></a></li><li><a href=\"/en-US/docs/Web/MathML/Element/msub\"><code>&lt;msub&gt;</code></a></li><li><a href=\"/en-US/docs/Web/MathML/Element/msubsup\"><code>&lt;msubsup&gt;</code></a></li><li><a href=\"/en-US/docs/Web/MathML/Element/msup\"><code>&lt;msup&gt;</code></a></li><li><a href=\"/en-US/docs/Web/MathML/Element/mtable\"><code>&lt;mtable&gt;</code></a></li><li><a href=\"/en-US/docs/Web/MathML/Element/mtd\"><code>&lt;mtd&gt;</code></a></li><li><a href=\"/en-US/docs/Web/MathML/Element/mtext\"><code>&lt;mtext&gt;</code></a></li><li><a href=\"/en-US/docs/Web/MathML/Element/mtr\"><code>&lt;mtr&gt;</code></a></li><li><a href=\"/en-US/docs/Web/MathML/Element/munder\"><code>&lt;munder&gt;</code></a></li><li><a href=\"/en-US/docs/Web/MathML/Element/munderover\"><code>&lt;munderover&gt;</code></a></li><li><a href=\"/en-US/docs/Web/MathML/Element/semantics\"><code>&lt;semantics&gt;</code></a></li></ol>\n    </details>\n  </li>\n  <li class=\"toggle\">\n    <details open=\"\">\n      <summary>Global attributes</summary>\n      <ol><li><a href=\"/en-US/docs/Web/MathML/Global_attributes/dir\"><code>dir</code></a></li><li><a href=\"/en-US/docs/Web/MathML/Global_attributes/displaystyle\"><code>displaystyle</code></a></li><li><a href=\"/en-US/docs/Web/MathML/Global_attributes/href\"><code>href</code></a><abbr class=\"icon icon-nonstandard\" title=\"Non-standard. Check cross-browser support before using.\">\n    <span class=\"visually-hidden\">Non-standard</span>\n</abbr></li><li><a href=\"/en-US/docs/Web/MathML/Global_attributes/mathbackground\"><code>mathbackground</code></a><abbr class=\"icon icon-deprecated\" title=\"Deprecated. Not for use in new websites.\">\n  <span class=\"visually-hidden\">Deprecated</span>\n</abbr></li><li><a href=\"/en-US/docs/Web/MathML/Global_attributes/mathcolor\"><code>mathcolor</code></a><abbr class=\"icon icon-deprecated\" title=\"Deprecated. Not for use in new websites.\">\n  <span class=\"visually-hidden\">Deprecated</span>\n</abbr></li><li><em><a href=\"/en-US/docs/Web/MathML/Global_attributes/mathsize\" aria-current=\"page\"><code>mathsize</code></a><abbr class=\"icon icon-deprecated\" title=\"Deprecated. Not for use in new websites.\">\n  <span class=\"visually-hidden\">Deprecated</span>\n</abbr></em></li><li><a href=\"/en-US/docs/Web/MathML/Global_attributes/scriptlevel\"><code>scriptlevel</code></a></li></ol>\n    </details>\n  </li>\n  <li><a href=\"/en-US/docs/Web/MathML/Attribute\">Attributes</a></li>\n  <li><strong>Examples</strong></li>\n  <li>\n    <ol>\n    <li><a href=\"/en-US/docs/Web/MathML/Examples/Deriving_the_Quadratic_Formula\">Deriving the Quadratic Formula</a></li>\n    <li><a href=\"/en-US/docs/Web/MathML/Examples/MathML_Pythagorean_Theorem\">Proving the Pythagorean theorem</a></li>\n    </ol>\n  </li>\n </ol>\n","sidebarMacro":"MathMLRef","body":[{"type":"prose","value":{"id":null,"title":null,"isH3":false,"content":"<div class=\"notecard deprecated\" id=\"sect1\"><p><strong>Deprecated:</strong> This feature is no longer recommended. Though some browsers might still support it, it may have already been removed from the relevant web standards, may be in the process of being dropped, or may only be kept for compatibility purposes. Avoid using it, and update existing code if possible; see the <a href=\"#browser_compatibility\">compatibility table</a> at the bottom of this page to guide your decision. Be aware that this feature may cease to work at any time.</p></div>\n<p>The <strong><code>mathsize</code></strong> <a href=\"/en-US/docs/Web/MathML/Global_attributes\">global attribute</a> sets the <a href=\"/en-US/docs/Web/CSS/font-size\">font-size</a> of a MathML element.</p>\n<div class=\"notecard note\" id=\"sect2\">\n  <p><strong>Note:</strong> Use CSS for styling MathML whenever possible. The <code>mathsize</code> attribute should only be included for applications that are not CSS-aware and will be overridden by the CSS <code>font-size</code> property, if set.</p>\n</div>"}},{"type":"prose","value":{"id":"syntax","title":"Syntax","isH3":false,"content":"<div class=\"code-example\"><p class=\"example-header\"><span class=\"language-name\">html</span></p><pre class=\"brush: html notranslate\"><code><span class=\"token comment\">&lt;!-- &lt;length&gt; values --&gt;</span>\n<span class=\"token tag\"><span class=\"token tag\"><span class=\"token punctuation\">&lt;</span>math</span> <span class=\"token attr-name\">mathsize</span><span class=\"token attr-value\"><span class=\"token punctuation attr-equals\">=</span><span class=\"token punctuation\">\"</span>12px<span class=\"token punctuation\">\"</span></span><span class=\"token punctuation\">&gt;</span></span>\n<span class=\"token tag\"><span class=\"token tag\"><span class=\"token punctuation\">&lt;</span>math</span> <span class=\"token attr-name\">mathsize</span><span class=\"token attr-value\"><span class=\"token punctuation attr-equals\">=</span><span class=\"token punctuation\">\"</span>0.8em<span class=\"token punctuation\">\"</span></span><span class=\"token punctuation\">&gt;</span></span>\n\n<span class=\"token comment\">&lt;!-- &lt;percentage&gt; values --&gt;</span>\n<span class=\"token tag\"><span class=\"token tag\"><span class=\"token punctuation\">&lt;</span>math</span> <span class=\"token attr-name\">mathsize</span><span class=\"token attr-value\"><span class=\"token punctuation attr-equals\">=</span><span class=\"token punctuation\">\"</span>80%<span class=\"token punctuation\">\"</span></span><span class=\"token punctuation\">&gt;</span></span>\n</code></pre></div>"}},{"type":"prose","value":{"id":"values","title":"Values","isH3":true,"content":"<dl>\n  <dt id=\"length\"><a href=\"/en-US/docs/Web/CSS/length\"><code>&lt;length&gt;</code></a></dt>\n  <dd>\n    <p>A positive <a href=\"/en-US/docs/Web/CSS/length\"><code>&lt;length&gt;</code></a> value. For most font-relative units (such as <code>em</code> and <code>ex</code>), the font size is relative to the parent element's font size.</p>\n  </dd>\n  <dt id=\"percentage\"><a href=\"/en-US/docs/Web/CSS/percentage\"><code>&lt;percentage&gt;</code></a></dt>\n  <dd>\n    <p>A positive <a href=\"/en-US/docs/Web/CSS/percentage\"><code>&lt;percentage&gt;</code></a> value, relative to the parent element's font size.</p>\n  </dd>\n</dl>\n<div class=\"notecard note\" id=\"sect3\">\n  <p><strong>Note:</strong> Some browsers may also accept <a href=\"/en-US/docs/Web/MathML/Values#legacy_mathml_lengths\">legacy MathML lengths</a>.</p>\n</div>"}},{"type":"specifications","value":{"title":"Specifications","id":"specifications","isH3":false,"specifications":[{"bcdSpecificationURL":"https://w3c.github.io/mathml-core/#dfn-mathsize","title":"MathML Core"}],"query":"mathml.global_attributes.mathsize"}},{"type":"prose","value":{"id":null,"title":null,"isH3":false,"content":"<ul>\n  <li>\n    In MathML 3 and earlier versions, keywords <code>small</code>, <code>normal</code>, and <code>big</code> as\n    well as the MathML3-specific syntax for lengths was supported.\n    Since MathML Core, the syntax matches CSS\n    <a href=\"/en-US/docs/Web/CSS/length-percentage\"><code>&lt;length-percentage&gt;</code></a> values.\n  </li>\n  <li>\n    This attribute was designed for MathML applications that are not CSS-aware.\n    Since MathML Core, the use of equivalent CSS is recommended instead.\n  </li>\n</ul>"}},{"type":"browser_compatibility","value":{"title":"Browser compatibility","id":"browser_compatibility","isH3":false,"query":"mathml.global_attributes.mathsize"}},{"type":"prose","value":{"id":"see_also","title":"See also","isH3":false,"content":"<ul>\n  <li>All <a href=\"/en-US/docs/Web/MathML/Global_attributes\">global attributes</a>.</li>\n  <li><a href=\"/en-US/docs/Web/CSS/font-size\"><code>font-size</code></a></li>\n</ul>"}}],"toc":[{"text":"Syntax","id":"syntax"},{"text":"Specifications","id":"specifications"},{"text":"Browser compatibility","id":"browser_compatibility"},{"text":"See also","id":"see_also"}],"summary":"The mathsize global attribute sets the font-size of a MathML element.","popularity":0,"modified":"2023-07-17T23:05:13.000Z","source":{"folder":"en-us/web/mathml/global_attributes/mathsize","github_url":"https://github.com/mdn/content/blob/main/files/en-us/web/mathml/global_attributes/mathsize/index.md","last_commit_url":"https://github.com/mdn/content/commit/07f0cf4375aaa02e1071d8bd0e8518db7609b7a9","filename":"index.md"},"short_title":"mathsize","parents":[{"uri":"/en-US/docs/Web","title":"References"},{"uri":"/en-US/docs/Web/MathML","title":"MathML"},{"uri":"/en-US/docs/Web/MathML/Global_attributes","title":"Global attributes"},{"uri":"/en-US/docs/Web/MathML/Global_attributes/mathsize","title":"mathsize"}],"pageTitle":"mathsize - MathML | MDN","noIndexing":false}}