{"isMarkdown":true,"isTranslated":false,"isActive":true,"flaws":{},"title":"XPathExpression","mdn_url":"/en-US/docs/Web/API/XPathExpression","locale":"en-US","native":"English (US)","browserCompat":["api.XPathExpression"],"summary":"This interface is a compiled XPath expression that can be evaluated on a document or specific node to return information from its DOM tree.","popularity":0.0011,"modified":"2023-07-07T07:19:19.000Z","source":{"folder":"en-us/web/api/xpathexpression","github_url":"https://github.com/mdn/content/blob/main/files/en-us/web/api/xpathexpression/index.md","last_commit_url":"https://github.com/mdn/content/commit/acfe8c9f1f4145f77653a2bc64a9744b001358dc","filename":"index.md"},"short_title":"XPathExpression","parents":[{"uri":"/en-US/docs/Web","title":"References"},{"uri":"/en-US/docs/Web/API","title":"Web APIs"},{"uri":"/en-US/docs/Web/API/XPathExpression","title":"XPathExpression"}],"pageTitle":"XPathExpression - Web APIs | MDN","noIndexing":false,"hash":"3bd108ac644a1d5431c3d5cd952b648d384bee5e871772dc205aa5b79d0a004c"}