{"isMarkdown":true,"isTranslated":false,"isActive":true,"flaws":{},"title":"ElementInternals: ariaRelevant property","mdn_url":"/en-US/docs/Web/API/ElementInternals/ariaRelevant","locale":"en-US","native":"English (US)","browserCompat":["api.ElementInternals.ariaRelevant"],"summary":"The ariaRelevant property of the ElementInternals interface reflects the value of the aria-relevant attribute, which indicates what notifications the user agent will trigger when the accessibility tree within a live region is modified. This is used to describe what changes in an aria-live region are relevant and should be announced.","popularity":0,"modified":"2023-12-08T11:07:32.000Z","source":{"folder":"en-us/web/api/elementinternals/ariarelevant","github_url":"https://github.com/mdn/content/blob/main/files/en-us/web/api/elementinternals/ariarelevant/index.md","last_commit_url":"https://github.com/mdn/content/commit/ce10da0e9d23d241b175d8d68bf93507734b7c48","filename":"index.md"},"short_title":"ariaRelevant","parents":[{"uri":"/en-US/docs/Web","title":"References"},{"uri":"/en-US/docs/Web/API","title":"Web APIs"},{"uri":"/en-US/docs/Web/API/ElementInternals","title":"ElementInternals"},{"uri":"/en-US/docs/Web/API/ElementInternals/ariaRelevant","title":"ariaRelevant"}],"pageTitle":"ElementInternals: ariaRelevant property - Web APIs | MDN","noIndexing":false,"hash":"8d6f39d1d4c7f79d78f11dbce04bbff9787c39970381ec7879a7652cce0dbb1c"}