{"isMarkdown":true,"isTranslated":false,"isActive":true,"flaws":{},"title":"BroadcastChannel: close() method","mdn_url":"/en-US/docs/Web/API/BroadcastChannel/close","locale":"en-US","native":"English (US)","browserCompat":["api.BroadcastChannel.close"],"baseline":{"baseline":"low","baseline_low_date":"2022-03-15","support":{"chrome":"60","chrome_android":"60","edge":"79","firefox":"57","firefox_android":"57","safari":"15.4","safari_ios":"15.4"}},"summary":"The BroadcastChannel.close() terminates the connection to\n  the underlying channel, allowing the object to be garbage collected.\n  This is a necessary step to perform\n  as there is no other way for a browser to know\n  that this channel is not needed anymore.","popularity":0.0011,"modified":"2023-04-07T06:13:50.000Z","source":{"folder":"en-us/web/api/broadcastchannel/close","github_url":"https://github.com/mdn/content/blob/main/files/en-us/web/api/broadcastchannel/close/index.md","last_commit_url":"https://github.com/mdn/content/commit/1f216a70d94c3901c5767e6108a29daa48edc070","filename":"index.md"},"short_title":"close()","parents":[{"uri":"/en-US/docs/Web","title":"References"},{"uri":"/en-US/docs/Web/API","title":"Web APIs"},{"uri":"/en-US/docs/Web/API/BroadcastChannel","title":"BroadcastChannel"},{"uri":"/en-US/docs/Web/API/BroadcastChannel/close","title":"close()"}],"pageTitle":"BroadcastChannel: close() method - Web APIs | MDN","noIndexing":false,"hash":"93c50570b8246c2200f7d2bba43692e97bbc2b9c67f266d7300addecf34548bb"}