{"isMarkdown":true,"isTranslated":false,"isActive":true,"flaws":{},"title":"ProgressEvent","mdn_url":"/en-US/docs/Web/API/ProgressEvent","locale":"en-US","native":"English (US)","browserCompat":["api.ProgressEvent"],"summary":"The ProgressEvent interface represents events measuring progress of an underlying process, like an HTTP request (for an XMLHttpRequest, or the loading of the underlying resource of an <img>, <audio>, <video>, <style> or <link>).","popularity":0.0069,"modified":"2023-11-08T06:06:49.000Z","source":{"folder":"en-us/web/api/progressevent","github_url":"https://github.com/mdn/content/blob/main/files/en-us/web/api/progressevent/index.md","last_commit_url":"https://github.com/mdn/content/commit/0a726c0a04ab286873ad91b5ddee478dd938832d","filename":"index.md"},"short_title":"ProgressEvent","parents":[{"uri":"/en-US/docs/Web","title":"References"},{"uri":"/en-US/docs/Web/API","title":"Web APIs"},{"uri":"/en-US/docs/Web/API/ProgressEvent","title":"ProgressEvent"}],"pageTitle":"ProgressEvent - Web APIs | MDN","noIndexing":false,"hash":"565f0a053716dbddd83a05ddf4c2d01f44af00fd18c1bd63aeda76fd9629ea70"}