{"isMarkdown":true,"isTranslated":false,"isActive":true,"flaws":{},"title":"XRPose: angularVelocity property","mdn_url":"/en-US/docs/Web/API/XRPose/angularVelocity","locale":"en-US","native":"English (US)","browserCompat":["api.XRPose.angularVelocity"],"summary":"The angularVelocity read-only property of the\n  XRPose interface is a DOMPointReadOnly describing\n  the angular velocity in radians per second relative to the base\n  XRSpace.","popularity":0,"modified":"2023-04-08T07:02:14.000Z","source":{"folder":"en-us/web/api/xrpose/angularvelocity","github_url":"https://github.com/mdn/content/blob/main/files/en-us/web/api/xrpose/angularvelocity/index.md","last_commit_url":"https://github.com/mdn/content/commit/6788d086c530ae04793a497d12863db3d8adf040","filename":"index.md"},"short_title":"angularVelocity","parents":[{"uri":"/en-US/docs/Web","title":"References"},{"uri":"/en-US/docs/Web/API","title":"Web APIs"},{"uri":"/en-US/docs/Web/API/XRPose","title":"XRPose"},{"uri":"/en-US/docs/Web/API/XRPose/angularVelocity","title":"angularVelocity"}],"pageTitle":"XRPose: angularVelocity property - Web APIs | MDN","noIndexing":false,"hash":"03344b50ab98b01e0ae239ab4514ef6fde96aa2df5c66a0c04875923e4668925"}