{"isMarkdown":true,"isTranslated":false,"isActive":true,"flaws":{},"title":"The event loop","mdn_url":"/en-US/docs/Web/JavaScript/Event_loop","locale":"en-US","native":"English (US)","summary":"JavaScript has a runtime model based on an event loop, which is responsible for executing the code, collecting and processing events, and executing queued sub-tasks. This model is quite different from models in other languages like C and Java.","popularity":0.0937,"modified":"2023-09-12T03:52:28.000Z","source":{"folder":"en-us/web/javascript/event_loop","github_url":"https://github.com/mdn/content/blob/main/files/en-us/web/javascript/event_loop/index.md","last_commit_url":"https://github.com/mdn/content/commit/4f86aad2b0b66c0d2041354ec81400c574ab56ca","filename":"index.md"},"short_title":"The event loop","parents":[{"uri":"/en-US/docs/Web","title":"References"},{"uri":"/en-US/docs/Web/JavaScript","title":"JavaScript"},{"uri":"/en-US/docs/Web/JavaScript/Event_loop","title":"The event loop"}],"pageTitle":"The event loop - JavaScript | MDN","noIndexing":false,"hash":"61b5e054d51b2543f0f9e4f60ee54431bf679bdd1ce75d8be0ff28795aa11580"}