{"isMarkdown":true,"isTranslated":false,"isActive":true,"flaws":{},"title":"MediaKeySystemAccess","mdn_url":"/en-US/docs/Web/API/MediaKeySystemAccess","locale":"en-US","native":"English (US)","browserCompat":["api.MediaKeySystemAccess"],"summary":"The MediaKeySystemAccess interface of the Encrypted Media Extensions API provides access to a Key System for decryption and/or a content protection provider. You can request an instance of this object using the Navigator.requestMediaKeySystemAccess() method.","popularity":0.0017,"modified":"2023-03-14T07:47:03.000Z","source":{"folder":"en-us/web/api/mediakeysystemaccess","github_url":"https://github.com/mdn/content/blob/main/files/en-us/web/api/mediakeysystemaccess/index.md","last_commit_url":"https://github.com/mdn/content/commit/7f21f4fadd056c2c6afd46f9ad2f172883f6db05","filename":"index.md"},"short_title":"MediaKeySystemAccess","parents":[{"uri":"/en-US/docs/Web","title":"References"},{"uri":"/en-US/docs/Web/API","title":"Web APIs"},{"uri":"/en-US/docs/Web/API/MediaKeySystemAccess","title":"MediaKeySystemAccess"}],"pageTitle":"MediaKeySystemAccess - Web APIs | MDN","noIndexing":false,"hash":"5342cdf7f3fb44273d7f5f129e89c4651bf2cabbc28f87434a84fbc135d906dd"}