{"isMarkdown":true,"isTranslated":false,"isActive":true,"flaws":{},"title":"Document: visibilitychange event","mdn_url":"/en-US/docs/Web/API/Document/visibilitychange_event","locale":"en-US","native":"English (US)","browserCompat":["api.Document.visibilitychange_event"],"summary":"The visibilitychange event is fired at the document when the contents of its tab have become visible or have been hidden.","popularity":0.0314,"modified":"2023-04-07T05:52:28.000Z","source":{"folder":"en-us/web/api/document/visibilitychange_event","github_url":"https://github.com/mdn/content/blob/main/files/en-us/web/api/document/visibilitychange_event/index.md","last_commit_url":"https://github.com/mdn/content/commit/41a8b9c9832359d445d136b6d7a8a28737badc6b","filename":"index.md"},"short_title":"visibilitychange","parents":[{"uri":"/en-US/docs/Web","title":"References"},{"uri":"/en-US/docs/Web/API","title":"Web APIs"},{"uri":"/en-US/docs/Web/API/Document","title":"Document"},{"uri":"/en-US/docs/Web/API/Document/visibilitychange_event","title":"visibilitychange"}],"pageTitle":"Document: visibilitychange event - Web APIs | MDN","noIndexing":false,"hash":"e99c80cef42b7573ede74b62ac010563fd02594ad2eddd0f7f712b781d4462fc"}