{"isMarkdown":true,"isTranslated":false,"isActive":true,"flaws":{},"title":"Range: setStart() method","mdn_url":"/en-US/docs/Web/API/Range/setStart","locale":"en-US","native":"English (US)","browserCompat":["api.Range.setStart"],"summary":"The Range.setStart() method sets the start position of a\n  Range.","popularity":0.0044,"modified":"2023-04-07T19:46:21.000Z","source":{"folder":"en-us/web/api/range/setstart","github_url":"https://github.com/mdn/content/blob/main/files/en-us/web/api/range/setstart/index.md","last_commit_url":"https://github.com/mdn/content/commit/c58e8c1dd6ecbcb63894c7dd17fb9495b9511b4e","filename":"index.md"},"short_title":"setStart()","parents":[{"uri":"/en-US/docs/Web","title":"References"},{"uri":"/en-US/docs/Web/API","title":"Web APIs"},{"uri":"/en-US/docs/Web/API/Range","title":"Range"},{"uri":"/en-US/docs/Web/API/Range/setStart","title":"setStart()"}],"pageTitle":"Range: setStart() method - Web APIs | MDN","noIndexing":false,"hash":"b6f57a304971c55f88608182c02a635b0bb2f49f81401520d67e570edfd76a81"}