{"isMarkdown":true,"isTranslated":false,"isActive":true,"flaws":{},"title":"TextTrackCueList: getCueById() method","mdn_url":"/en-US/docs/Web/API/TextTrackCueList/getCueById","locale":"en-US","native":"English (US)","browserCompat":["api.TextTrackCueList.getCueById"],"summary":"The getCueById() method of the TextTrackCueList interface returns the first VTTCue in the list represented by the TextTrackCueList object whose identifier matches the value of id.","popularity":0,"modified":"2023-07-25T00:27:48.000Z","source":{"folder":"en-us/web/api/texttrackcuelist/getcuebyid","github_url":"https://github.com/mdn/content/blob/main/files/en-us/web/api/texttrackcuelist/getcuebyid/index.md","last_commit_url":"https://github.com/mdn/content/commit/592f6ec42e54981b6573b58ec0343c9aa8cbbda8","filename":"index.md"},"short_title":"getCueById()","parents":[{"uri":"/en-US/docs/Web","title":"References"},{"uri":"/en-US/docs/Web/API","title":"Web APIs"},{"uri":"/en-US/docs/Web/API/TextTrackCueList","title":"TextTrackCueList"},{"uri":"/en-US/docs/Web/API/TextTrackCueList/getCueById","title":"getCueById()"}],"pageTitle":"TextTrackCueList: getCueById() method - Web APIs | MDN","noIndexing":false,"hash":"308da3a4bf44ea8617a5202b5171eccddfa080a042c74b3a3f2ec01d88140d2e"}