{"isMarkdown":true,"isTranslated":false,"isActive":true,"flaws":{},"title":"MIME types (IANA media types)","mdn_url":"/en-US/docs/Web/HTTP/Basics_of_HTTP/MIME_types","locale":"en-US","native":"English (US)","summary":"A media type (also known as a Multipurpose Internet Mail Extensions or MIME type) indicates the nature and format of a document, file, or assortment of bytes.\n  MIME types are defined and standardized in IETF's RFC 6838.","popularity":0.1443,"modified":"2023-07-25T00:27:48.000Z","source":{"folder":"en-us/web/http/basics_of_http/mime_types","github_url":"https://github.com/mdn/content/blob/main/files/en-us/web/http/basics_of_http/mime_types/index.md","last_commit_url":"https://github.com/mdn/content/commit/592f6ec42e54981b6573b58ec0343c9aa8cbbda8","filename":"index.md"},"short_title":"MIME types (IANA media types)","parents":[{"uri":"/en-US/docs/Web","title":"References"},{"uri":"/en-US/docs/Web/HTTP","title":"HTTP"},{"uri":"/en-US/docs/Web/HTTP/Basics_of_HTTP","title":"Basics of HTTP"},{"uri":"/en-US/docs/Web/HTTP/Basics_of_HTTP/MIME_types","title":"MIME types (IANA media types)"}],"pageTitle":"MIME types (IANA media types) - HTTP | MDN","noIndexing":false,"hash":"c690bee35075b60c6e3055e40a0d50cede9f29c1fb45cb772467275497c70a16"}